fabricius/__init__.py
fabricius/app/main.py
fabricius/app/signals.py
fabricius/app/ui.py
fabricius/exceptions.py
fabricius/globals.py
fabricius/models/file.py
fabricius/models/renderer.py
fabricius/models/signal.py
fabricius/models/template.py
fabricius/py.typed
fabricius/readers/cookiecutter/config.py
fabricius/readers/cookiecutter/exceptions.py
fabricius/readers/cookiecutter/extensions.py
fabricius/readers/cookiecutter/hooks.py
fabricius/readers/cookiecutter/setup.py
fabricius/readers/README.md
fabricius/renderers/__init__.py
fabricius/renderers/jinja_renderer.py
fabricius/renderers/mustache.py
fabricius/renderers/python_format.py
fabricius/renderers/python_string_template.py
fabricius/renderers/utils.py
fabricius/types.py
fabricius/utils.py
LICENSE
README.md
fabricius-0.2.0.dist-info/LICENSE
fabricius-0.2.0.dist-info/METADATA
fabricius-0.2.0.dist-info/WHEEL
fabricius-0.2.0.dist-info/RECORD
