Metadata-Version: 2.1
Name: fabricius
Version: 0.2.0
Summary: Fabricius: The supportive templating engine for Python!
Home-page: https://github.com/Predeactor/Fabricius
License: MIT
Keywords: cookiecutter,template,project,scaffold,pyscaffold
Author: Predeactor
Author-email: pro.julien.mauroy@gmail.com
Requires-Python: >=3.10,<4.0
Classifier: Development Status :: 2 - Pre-Alpha
Classifier: Intended Audience :: Developers
Classifier: Intended Audience :: End Users/Desktop
Classifier: License :: OSI Approved :: MIT License
Classifier: Natural Language :: English
Classifier: Operating System :: OS Independent
Classifier: Programming Language :: Python :: 3
Classifier: Programming Language :: Python :: 3.10
Classifier: Programming Language :: Python :: 3.11
Classifier: Programming Language :: Python :: 3.10
Classifier: Programming Language :: Python :: Implementation :: CPython
Classifier: Topic :: Software Development :: Build Tools
Classifier: Topic :: Software Development :: Libraries :: Python Modules
Classifier: Topic :: Utilities
Classifier: Typing :: Typed
Provides-Extra: docs
Requires-Dist: Sphinx (>=5.0.2,<6.0.0) ; extra == "docs"
Requires-Dist: chevron (>=0.14.0,<0.15.0)
Requires-Dist: click (>=8.1.3,<9.0.0)
Requires-Dist: furo (>=2022.6.21,<2023.0.0) ; extra == "docs"
Requires-Dist: inflection (>=0.5.1,<0.6.0)
Requires-Dist: jinja2 (>=3.1.2,<4.0.0)
Requires-Dist: jinja2-time (>=0.2.0,<0.3.0)
Requires-Dist: pyyaml (>=6.0,<7.0)
Requires-Dist: rich (>=12.4.4,<13.0.0)
Requires-Dist: slugify (>=0.0.1,<0.0.2)
Requires-Dist: sphinx-autobuild (>=2021.3.14,<2022.0.0) ; extra == "docs"
Requires-Dist: typing-extensions (>=4.2.0,<5.0.0)
Project-URL: Documentation, https://fabricius.readthedocs.org
Project-URL: Repository, https://github.com/Predeactor/Fabricius
